swampdragon_live/__init__.py
swampdragon_live/classes.py
swampdragon_live/models.py
swampdragon_live/pushers.py
swampdragon_live/routers.py
swampdragon_live/utils.py
swampdragon_live/static/swampdragon/js/live/swampdragon.live.js
swampdragon_live/templatetags/__init__.py
swampdragon_live/templatetags/swampdragon_live.py
SwampDragon_live-0.0.7a0.dist-info/DESCRIPTION.rst
SwampDragon_live-0.0.7a0.dist-info/METADATA
SwampDragon_live-0.0.7a0.dist-info/metadata.json
SwampDragon_live-0.0.7a0.dist-info/RECORD
SwampDragon_live-0.0.7a0.dist-info/top_level.txt
SwampDragon_live-0.0.7a0.dist-info/WHEEL
