Metadata-Version: 2.0
Name: SwampDragon-live
Version: 0.0.7a0
Summary: SwampDragon-live is an extension to Django and SwampDragon which adds support for live updating Django template snippets on model changes.
Home-page: https://github.com/mback2k/swampdragon-live
Author: Marc Hoersken
Author-email: info@marc-hoersken.de
License: MIT
Platform: UNKNOWN
Classifier: Topic :: Internet :: WWW/HTTP :: Dynamic Content
Classifier: Intended Audience :: Developers
Classifier: License :: OSI Approved :: MIT License
Classifier: Programming Language :: Python
Classifier: Topic :: Software Development :: Libraries :: Python Modules
Classifier: Development Status :: 3 - Alpha
Classifier: Operating System :: OS Independent
Requires-Dist: SwampDragon
Requires-Dist: SwampDragon-auth
